MANIFEST.in
README.rst
common-requirements.txt
py2-requirements.txt
py3-requirements.txt
setup.cfg
setup.py
amazon_dash/__init__.py
amazon_dash/_compat.py
amazon_dash/audio.py
amazon_dash/config.py
amazon_dash/confirmations.py
amazon_dash/discovery.py
amazon_dash/exceptions.py
amazon_dash/execute.py
amazon_dash/hack.wav
amazon_dash/listener.py
amazon_dash/management.py
amazon_dash/scan.py
amazon_dash/wifi.py
amazon_dash.egg-info/PKG-INFO
amazon_dash.egg-info/SOURCES.txt
amazon_dash.egg-info/dependency_links.txt
amazon_dash.egg-info/not-zip-safe
amazon_dash.egg-info/pbr.json
amazon_dash.egg-info/requires.txt
amazon_dash.egg-info/top_level.txt
amazon_dash/install/__init__.py
amazon_dash/install/__main__.py
amazon_dash/install/amazon-dash.yml
amazon_dash/install/exceptions.py
amazon_dash/install/services/amazon-dash.service
amazon_dash/tests/__init__.py
amazon_dash/tests/_compat.py
amazon_dash/tests/base.py
amazon_dash/tests/test_audio.py
amazon_dash/tests/test_config.py
amazon_dash/tests/test_confirmations.py
amazon_dash/tests/test_discovery.py
amazon_dash/tests/test_execute.py
amazon_dash/tests/test_install.py
amazon_dash/tests/test_listener.py
amazon_dash/tests/test_wifi.py
scripts/amazon-dash