Metadata-Version: 1.1
Name: amazon-dash
Version: 1.4.0
Summary: Hack your Amazon Dash to run what you want.
